ovspy
