Metadata-Version: 2.1
Name: ovspy
Version: 0.1.0b1
Summary: Open vSwitch Mnipulation Library
Home-page: https://github.com/kamaboko123/ovspy
Author: kamaboko123
Author-email: 6112062+kamaboko123@users.noreply.github.com
License: MIT
Platform: UNKNOWN
Classifier: Programming Language :: Python :: 3.5
